setup.py
dcard/__init__.py
dcard.egg-info/PKG-INFO
dcard.egg-info/SOURCES.txt
dcard.egg-info/dependency_links.txt
dcard.egg-info/top_level.txt