Metadata-Version: 1.0
Name: dcard
Version: 0.1.0
Summary: Dcard python module
Home-page: UNKNOWN
Author: Dcard
Author-email: UNKNOWN
License: MIT
Platform: UNKNOWN
